rofi_rbw/__init__.py
rofi_rbw/__main__.py
rofi_rbw/abstractionhelper.py
rofi_rbw/argument_parsing.py
rofi_rbw/cache.py
rofi_rbw/paths.py
rofi_rbw/rbw.py
rofi_rbw/rofi_rbw.py
rofi_rbw/clipboarder/__init__.py
rofi_rbw/clipboarder/clipboarder.py
rofi_rbw/clipboarder/noop.py
rofi_rbw/clipboarder/wlclip.py
rofi_rbw/clipboarder/xclip.py
rofi_rbw/clipboarder/xsel.py
rofi_rbw/models/EntryType.py
rofi_rbw/models/__init__.py
rofi_rbw/models/action.py
rofi_rbw/models/card.py
rofi_rbw/models/credentials.py
rofi_rbw/models/detailed_entry.py
rofi_rbw/models/entry.py
rofi_rbw/models/field.py
rofi_rbw/models/keybinding.py
rofi_rbw/models/note.py
rofi_rbw/models/targets.py
rofi_rbw/selector/__init__.py
rofi_rbw/selector/bemenu.py
rofi_rbw/selector/fuzzel.py
rofi_rbw/selector/rofi.py
rofi_rbw/selector/selector.py
rofi_rbw/selector/wofi.py
rofi_rbw/typer/__init__.py
rofi_rbw/typer/dotool.py
rofi_rbw/typer/noop.py
rofi_rbw/typer/typer.py
rofi_rbw/typer/wtype.py
rofi_rbw/typer/xdotool.py
rofi_rbw/typer/ydotool.py
rofi_rbw-1.6.0.dist-info/METADATA
rofi_rbw-1.6.0.dist-info/WHEEL
rofi_rbw-1.6.0.dist-info/entry_points.txt
rofi_rbw-1.6.0.dist-info/licenses/LICENSE
rofi_rbw-1.6.0.dist-info/RECORD
