Metadata-Version: 2.4
Name: rofi-rbw
Version: 1.6.0
Summary: Rofi frontend for Bitwarden
Project-URL: homepage, https://github.com/fdw/rofi-rbw
Project-URL: repository, https://github.com/fdw/rofi-rbw
Author-email: Fabian Winter <5821180+fdw@users.noreply.github.com>
License: MIT
License-File: LICENSE
Requires-Python: >=3.10
Requires-Dist: configargparse<2.0.0,>1.3
